{
  "_class": "symbolInstance",
  "do_objectID": "6243E500-EDEA-4A29-BA52-1DEAFC6CADF8",
  "exportOptions": {
    "_class": "exportOptions",
    "do_objectID": "7FA40C66-BBDB-4859-9B68-B93A80D24178",
    "exportFormats": [
    ],
    "includedLayerIds": [
    ],
    "layerOptions": 0,
    "shouldTrim": false
  },
  "frame": {
    "_class": "rect",
    "constrainProportions": false,
    "do_objectID": "F64AE5FF-E481-4ECE-A7F2-28E8579A55F2",
    "height": 48,
    "width": 360,
    "x": 0,
    "y": 592
  },
  "horizontalSpacing": 0,
  "isFlippedHorizontal": false,
  "isFlippedVertical": false,
  "isLocked": false,
  "isVisible": true,
  "layerListExpandedType": 0,
  "name": "navbar",
  "nameIsFixed": false,
  "overrideValues": [
  ],
  "resizingConstraint": 63,
  "resizingType": 0,
  "rotation": 0,
  "scale": 1,
  "shouldBreakMaskChain": false,
  "style": {
    "_class": "style",
    "do_objectID": "56CC2D3C-D8DE-4724-825E-628437D9B946",
    "endDecorationType": 0,
    "miterLimit": 10,
    "startDecorationType": 0
  },
  "symbolID": "0724E927-A9F9-4616-975A-B3BDE37339AB",
  "verticalSpacing": 0
}