{
  "_class": "shapeGroup",
  "booleanOperation": 0,
  "clippingMaskMode": 0,
  "do_objectID": "45D76D5E-88F3-4C3B-A5EC-002D32085812",
  "exportOptions": {
    "_class": "exportOptions",
    "do_objectID": "84E2B4BD-D70A-4BD2-B25D-0E13999738D2",
    "exportFormats": [
    ],
    "includedLayerIds": [
    ],
    "layerOptions": 0,
    "shouldTrim": false
  },
  "frame": {
    "_class": "rect",
    "constrainProportions": false,
    "do_objectID": "A48E5875-F8C8-43C5-943A-36759D1F5243",
    "height": 143,
    "width": 355,
    "x": 8,
    "y": 8
  },
  "hasClickThrough": false,
  "hasClippingMask": true,
  "isFixedToViewport": false,
  "isFlippedHorizontal": false,
  "isFlippedVertical": false,
  "isLocked": false,
  "isVisible": true,
  "layerListExpandedType": 1,
  "layers": [
    {
      "class": "rectangle",
      "id": "B66BA8C5-3080-423A-AEF6-AD191A0589BB"
    }
  ],
  "name": "Body",
  "nameIsFixed": true,
  "resizingConstraint": 18,
  "resizingType": 0,
  "rotation": 0,
  "shouldBreakMaskChain": true,
  "style": {
    "_class": "style",
    "blur": {
      "_class": "blur",
      "center": "{0.5, 0.5}",
      "do_objectID": "32711509-6AE0-43EA-8E9B-F090C3FA3C86",
      "isEnabled": true,
      "motionAngle": 0,
      "radius": 20,
      "type": 3
    },
    "do_objectID": "25B929E4-3CA6-4122-9B78-E8122E99DE19",
    "endMarkerType": 0,
    "fills": [
      {
        "_class": "fill",
        "color": {
          "_class": "color",
          "alpha": 0.8200000000000001,
          "blue": 0.9725490196078431,
          "green": 0.9725490196078431,
          "red": 0.9725490196078431
        },
        "fillType": 0,
        "isEnabled": true,
        "noiseIndex": 0,
        "noiseIntensity": 0,
        "patternFillType": 0,
        "patternTileScale": 1
      }
    ],
    "miterLimit": 10,
    "sharedObjectID": "547331C2-E3E1-4728-9B4E-882D6EC7C99B",
    "startMarkerType": 0,
    "windingRule": 1
  },
  "windingRule": 1
}