{
  "_class": "text",
  "attributedString": {
    "_class": "attributedString",
    "attributes": [
      {
        "_class": "stringAttribute",
        "attributes": {
          "MSAttributedStringColorAttribute": {
            "_class": "color",
            "alpha": 1,
            "blue": 0,
            "green": 0,
            "red": 0
          },
          "MSAttributedStringFontAttribute": {
            "_class": "fontDescriptor",
            "attributes": {
              "name": "SFUIDisplay-Bold",
              "size": 18
            }
          },
          "kerning": 0,
          "paragraphStyle": {
            "_class": "paragraphStyle",
            "alignment": 0,
            "allowsDefaultTighteningForTruncation": 0,
            "maximumLineHeight": 22,
            "minimumLineHeight": 22
          }
        },
        "length": 18,
        "location": 0
      }
    ],
    "string": "Notification Title"
  },
  "automaticallyDrawOnUnderlyingPath": false,
  "booleanOperation": 0,
  "do_objectID": "7738E43A-30B0-4363-9498-276335D1C1A8",
  "dontSynchroniseWithSymbol": false,
  "exportOptions": {
    "_class": "exportOptions",
    "do_objectID": "E3504EBA-55A1-4181-9279-59C56CB19894",
    "exportFormats": [
    ],
    "includedLayerIds": [
    ],
    "layerOptions": 0,
    "shouldTrim": false
  },
  "frame": {
    "_class": "rect",
    "constrainProportions": false,
    "do_objectID": "0A3DFCBE-E433-4ACB-A3D2-DA9D6177E976",
    "height": 22,
    "width": 278,
    "x": 24,
    "y": 68
  },
  "glyphBounds": "{{1, 3}, {134, 15}}",
  "isFixedToViewport": false,
  "isFlippedHorizontal": false,
  "isFlippedVertical": false,
  "isLocked": false,
  "isVisible": true,
  "layerListExpandedType": 0,
  "lineSpacingBehaviour": 2,
  "name": "Title",
  "nameIsFixed": true,
  "resizingConstraint": 10,
  "resizingType": 2,
  "rotation": 0,
  "shouldBreakMaskChain": false,
  "style": {
    "_class": "style",
    "do_objectID": "6AD6AD29-E3C3-48F9-824F-08A640F30169",
    "endMarkerType": 0,
    "miterLimit": 10,
    "sharedObjectID": "47B8EE90-DA2E-4BC5-939A-E93FC78A5956",
    "startMarkerType": 0,
    "textStyle": {
      "_class": "textStyle",
      "do_objectID": "99260909-CC61-49EC-9A02-CC8686C6C056",
      "encodedAttributes": {
        "MSAttributedStringColorAttribute": {
          "_class": "color",
          "alpha": 1,
          "blue": 0,
          "green": 0,
          "red": 0
        },
        "MSAttributedStringFontAttribute": {
          "_class": "fontDescriptor",
          "attributes": {
            "name": "SFUIDisplay-Bold",
            "size": 18
          }
        },
        "kerning": 0,
        "paragraphStyle": {
          "_class": "paragraphStyle",
          "alignment": 0,
          "allowsDefaultTighteningForTruncation": 0,
          "maximumLineHeight": 22,
          "minimumLineHeight": 22
        }
      },
      "verticalAlignment": 0
    },
    "windingRule": 1
  },
  "textBehaviour": 1
}